stenotype_vim.py
plover_stenotype_vim-1.1.0.dist-info/METADATA
plover_stenotype_vim-1.1.0.dist-info/WHEEL
plover_stenotype_vim-1.1.0.dist-info/entry_points.txt
plover_stenotype_vim-1.1.0.dist-info/top_level.txt
plover_stenotype_vim-1.1.0.dist-info/zip-safe
plover_stenotype_vim-1.1.0.dist-info/RECORD
