Metadata-Version: 2.1
Name: plover-stenotype-vim
Version: 1.1.0
Summary: Plover Stenotype layout but with extra keys for vim
Home-page: https://github.com/Josiah-tan/plover-stenotype-vim
Keywords: plover plover_plugin
Classifier: Programming Language :: Python :: 3.6
Classifier: Programming Language :: Python :: 3.7
Classifier: Programming Language :: Python :: 3.8
Classifier: Programming Language :: Python :: 3.9
Requires-Dist: plover (>=4.0.0.dev8)
